ghutter/__init__.py
ghutter/__main__.py
ghutter/github_api/__init__.py
ghutter/github_api/base/__init__.py
ghutter/github_api/base/base_query.py
ghutter/github_api/exceptions.py
ghutter/github_api/fetch_history_graph/__init__.py
ghutter/github_api/fetch_history_graph/fetch_history_graph.py
ghutter/github_api/fetch_history_graph/query.py
ghutter/utils/__init__.py
ghutter/utils/arguments.py
ghutter/utils/helpers.py
ghutter-0.1.1.dist-info/LICENSE
ghutter-0.1.1.dist-info/METADATA
ghutter-0.1.1.dist-info/WHEEL
ghutter-0.1.1.dist-info/entry_points.txt
ghutter-0.1.1.dist-info/RECORD
