Metadata-Version: 2.1
Name: ghutter
Version: 0.1.1
Summary: ghutter is a tool to recreate the history of a GitHub repository
Author: Roberto Bochet
Author-email: r@robertobochet.me
Requires-Python: >=3.11,<4.0
Classifier: Programming Language :: Python :: 3
Classifier: Programming Language :: Python :: 3.11
Requires-Dist: gql[aiohttp] (>=3.4.1,<4.0.0)
Requires-Dist: networkx (>=3.1,<4.0)
Requires-Dist: pydantic (>=2.3.0,<3.0.0)
Requires-Dist: pygraphviz (>=1.11,<2.0)
